work/test/imm_test_functional/imm_convert.v
`timescale 1ns / 1ps
//==============================================================
// Module: imm_decoder
// Function: Decode all RISC-V immediate types (I, S, B, J, U, SHAMT)
//==============================================================
module imm_decoder (
    input  wire [31:0] instruction_r,

    output wire [31:0] imm_i,
    output wire [31:0] imm_s,
    output wire [31:0] imm_b,
    output wire [31:0] imm_j,
    output wire [31:0] imm_u,
    output wire [31:0] shamt_imm
);

    // ----------------------------
    // Local opcode field decoding
    // ----------------------------
    wire [6:0] opcode = instruction_r[6:0];
    wire [2:0] funct3 = instruction_r[14:12];
    //wire [6:0] funct7 = instruction_r[31:25];

    // ----------------------------
    // Define opcode constants
    // ----------------------------
    localparam OPCODE_LUI      = 7'b0110111;
    localparam OPCODE_AUIPC    = 7'b0010111;
    localparam OPCODE_JAL      = 7'b1101111;
    localparam OPCODE_I_JALR   = 7'b1100111;
    localparam OPCODE_B        = 7'b1100011;
    localparam OPCODE_I_LOAD   = 7'b0000011;
    localparam OPCODE_S        = 7'b0100011;
    localparam OPCODE_I_ARITH  = 7'b0010011;

    // ----------------------------
    // Immediate types
    // ----------------------------
    // I-type (Load, JALR, Arithmetic except shifts)
    assign imm_i = (opcode == OPCODE_I_LOAD || opcode == OPCODE_I_JALR || (opcode == OPCODE_I_ARITH && !(funct3 == 3'b001 || funct3 == 3'b101))) ? {{20{instruction_r[31]}}, instruction_r[31:20]} : 32'b0;
    // S-type (Store)
    assign imm_s = (opcode == OPCODE_S) ? {{20{instruction_r[31]}}, instruction_r[31:25], instruction_r[11:7]} : 32'b0;
    // B-type (Branch)
    assign imm_b = (opcode == OPCODE_B) ? {{19{instruction_r[31]}}, instruction_r[31], instruction_r[7], instruction_r[30:25], instruction_r[11:8], 1'b0} : 32'b0;
    // U-type (LUI, AUIPC)
    assign imm_u = (opcode == OPCODE_LUI || opcode == OPCODE_AUIPC) ? {instruction_r[31:12], 12'b0} : 32'b0;
    // J-type (JAL)
    assign imm_j = (opcode == OPCODE_JAL) ? {{11{instruction_r[31]}}, instruction_r[31], instruction_r[19:12], instruction_r[20], instruction_r[30:21], 1'b0} : 32'b0;
    // SHAMT immediate (Shift instructions)
    assign shamt_imm = (opcode == OPCODE_I_ARITH && (funct3 == 3'b001 || funct3 == 3'b101)) ? {27'b0, instruction_r[24:20]} : 32'b0;
    
endmodule

work/test/imm_test_functional/tb_imm_convert.v
`timescale 1ns / 1ps

module tb_imm_decoder;
    reg [31:0] instruction;
    wire [31:0] imm_i;
    wire [31:0] imm_s;
    wire [31:0] imm_b;
    wire [31:0] imm_j;
    wire [31:0] imm_u;
    wire [31:0] shamt_imm;
    
    imm_decoder uut (
        .instruction_r(instruction),
        .imm_i(imm_i),
        .imm_s(imm_s),
        .imm_b(imm_b),
        .imm_j(imm_j),
        .imm_u(imm_u),
        .shamt_imm(shamt_imm)
    );
    task instr; input [31:0] a; begin
            instruction = a;
            #10;
        end
    endtask 
    
    
    initial begin
        $dumpfile("imm_test_functional.vcd");
        $dumpvars(0, tb_imm_decoder);
    end
    
    initial begin
        $monitor("%0t: instruction = %0h, imm_i = %0h, imm_s = %0h, imm_b = %0h, imm_j = %0h, imm_u = %0h, shamt_imm = %0h", $time, instruction, imm_i, imm_s, imm_b, imm_j, imm_u, shamt_imm);
        instr(32'h00A00093);
        instr(32'hFFB08113);
        instr(32'h07F00193);
        instr(32'h06400213);
        instr(32'h00822283);
        instr(32'h00C00313);
        instr(32'h000303E7);
        instr(32'h00100413);
        instr(32'h00341493);
        instr(32'h00145513);
        instr(32'h0C800593);
        instr(32'h0015A023);
        instr(32'h00500613);
        instr(32'h00500693);
        instr(32'h00D60463);
        instr(32'h00000713);
        instr(32'h02A00793);
        instr(32'h0080086F);
        instr(32'h00000893);
        instr(32'h07B00913);
        instr(32'h123459B7);
        instr(32'h12345A17);
        
        instr(32'h0015A0A3);
        instr(32'h0015A123);
        instr(32'h0015A223);

        $finish;
    end
endmodule

work/test/imm_test_functional/imm_test_functional.vcd
$date
   Mon Oct 27 13:44:31 2025
$end

$version
  2025.1.0
  $dumpfile ("imm_test_functional.vcd") 
$end

$timescale
  1ps
$end

$scope module tb_imm_decoder $end
$var reg 32 ! instruction [31:0] $end
$var wire 32 " imm_i [31:0] $end
$var wire 32 # imm_s [31:0] $end
$var wire 32 $ imm_b [31:0] $end
$var wire 32 % imm_j [31:0] $end
$var wire 32 & imm_u [31:0] $end
$var wire 32 ' shamt_imm [31:0] $end
$scope module uut $end
$var wire 32 ( instruction_r [31:0] $end
$var wire 32 " imm_i [31:0] $end
$var wire 32 # imm_s [31:0] $end
$var wire 32 $ imm_b [31:0] $end
$var wire 32 % imm_j [31:0] $end
$var wire 32 & imm_u [31:0] $end
$var wire 32 ' shamt_imm [31:0] $end
$var wire 7 ) opcode [6:0] $end
$var wire 3 * funct3 [2:0] $end
$upscope $end
$scope task instr $end
$var reg 32 + a [31:0] $end
$upscope $end
$upscope $end
$enddefinitions $end

#0
$dumpvars
b101000000000000010010011 !
b1010 "
b0 #
b0 $
b0 %
b0 &
b0 '
b101000000000000010010011 (
b10011 )
b0 *
b101000000000000010010011 +
$end

#10000
b11111111101100001000000100010011 !
b11111111111111111111111111111011 "
b11111111101100001000000100010011 (
b11111111101100001000000100010011 +

#20000
b111111100000000000110010011 !
b1111111 "
b111111100000000000110010011 (
b111111100000000000110010011 +

#30000
b110010000000000001000010011 !
b1100100 "
b110010000000000001000010011 (
b110010000000000001000010011 +

#40000
b100000100010001010000011 !
b1000 "
b100000100010001010000011 (
b11 )
b10 *
b100000100010001010000011 +

#50000
b110000000000001100010011 !
b1100 "
b110000000000001100010011 (
b10011 )
b0 *
b110000000000001100010011 +

#60000
b110000001111100111 !
b0 "
b110000001111100111 (
b1100111 )
b110000001111100111 +

#70000
b100000000010000010011 !
b1 "
b100000000010000010011 (
b10011 )
b100000000010000010011 +

#80000
b1101000001010010010011 !
b0 "
b11 '
b1101000001010010010011 (
b1 *
b1101000001010010010011 +

#90000
b101000101010100010011 !
b1 '
b101000101010100010011 (
b101 *
b101000101010100010011 +

#100000
b1100100000000000010110010011 !
b11001000 "
b0 '
b1100100000000000010110010011 (
b0 *
b1100100000000000010110010011 +

#110000
b101011010000000100011 !
b0 "
b101011010000000100011 (
b100011 )
b10 *
b101011010000000100011 +

#120000
b10100000000011000010011 !
b101 "
b10100000000011000010011 (
b10011 )
b0 *
b10100000000011000010011 +

#130000
b10100000000011010010011 !
b10100000000011010010011 (
b10100000000011010010011 +

#140000
b110101100000010001100011 !
b0 "
b1000 $
b110101100000010001100011 (
b1100011 )
b110101100000010001100011 +

#150000
b11100010011 !
b0 $
b11100010011 (
b10011 )
b11100010011 +

#160000
b10101000000000011110010011 !
b101010 "
b10101000000000011110010011 (
b10101000000000011110010011 +

#170000
b100000000000100001101111 !
b0 "
b1000 %
b100000000000100001101111 (
b1101111 )
b100000000000100001101111 +

#180000
b100010010011 !
b0 %
b100010010011 (
b10011 )
b100010010011 +

#190000
b111101100000000100100010011 !
b1111011 "
b111101100000000100100010011 (
b111101100000000100100010011 +

#200000
b10010001101000101100110110111 !
b0 "
b10010001101000101000000000000 &
b10010001101000101100110110111 (
b110111 )
b101 *
b10010001101000101100110110111 +

#210000
b10010001101000101101000010111 !
b10010001101000101101000010111 (
b10111 )
b10010001101000101101000010111 +

#220000
b101011010000010100011 !
b1 #
b0 &
b101011010000010100011 (
b100011 )
b10 *
b101011010000010100011 +

#230000
b101011010000100100011 !
b10 #
b101011010000100100011 (
b101011010000100100011 +
