hardware/bram_ip/verilog_mimicking/data_memory_mimic.v
`timescale 1ns / 1ps
module data_memory_mimic (
    input  wire        clka,
    input  wire        ena,
    input  wire        wea,
    input  wire [10:0] addra,  // 2048 = 2^11
    input  wire [7:0]  dina,
    output reg  [7:0]  douta
);

    // 8-bit x 2048 memory array
    reg [7:0] mem [0:2047];

    // Synchronous write, synchronous read
    always @(posedge clka) begin
        if (ena) begin
            if (wea)
                mem[addra] <= dina;     // write
            douta <= mem[addra];        // read (sync)
        end
    end

endmodule

work/test/tb/251026_tb_bram.v
`timescale 1ns / 1ps
module tb_bram;

    reg clka;
    reg ena;
    reg wea;
    reg [12:0] addra;
    reg [7:0] dina;
    wire [7:0] douta;

    data_memory_mimic dut (
        .clka(clka),
        .ena(ena),
        .wea(wea),
        .addra(addra),
        .dina(dina),
        .douta(douta)
    );

    initial clka = 0;
    always #5 clka = ~clka;

    task write_data;
        input [12:0] addr;
        input [7:0] data;
        begin
            @(negedge clka);
            ena  = 1;
            wea  = 1;
            addra = addr;
            dina  = data;
            @(negedge clka);
            wea  = 0;
            ena  = 0;
            $display("[%0t] WRITE: mem[%0d] = 0x%0h", $time, addr, data);
        end
    endtask

    task read_data;
        input [12:0] addr;
        begin
            @(negedge clka);
            ena  = 1;
            wea  = 0;
            addra = addr;
            @(negedge clka);
            $display("[%0t] READ:  mem[%0d] = 0x%0h", $time, addr, douta);
            ena  = 1;
        end
    endtask

    // --------------------------
    // MAIN TEST SEQUENCE
    // --------------------------
    initial begin
        $dumpfile("king.vcd");
        $dumpvars(0, tb_bram);

        // Init signals
        ena   = 0;
        wea   = 0;
        addra = 0;
        dina  = 0;

        // Wait a bit for stable sim
        #20;

        // Write first 5 memory locations
        write_data(0, 8'h11);
        write_data(1, 8'h22);
        write_data(2, 8'h33);
        write_data(3, 8'h44);
        write_data(4, 8'h55);

        // Read first 5 addresses
        $display("\n--- Reading first 5 addresses ---");
        read_data(0);
        read_data(1);
        read_data(2);
        read_data(3);
        read_data(4);

        // Optionally read all memory contents (example: 0-15)
        $display("\n--- Dumping first 16 addresses ---");
        repeat (16) begin
            addra = addra + 1;
            read_data(addra);
        end
        $writememh("mem_dump.hex", dut.mem);
        $display("Simulation finished.");
        #50;
        $finish;
    end

endmodule

work/vcd/data_mem_mimicking_byte_addressed_bram_ip.vcd
$date
   Sun Oct 26 20:16:10 2025
$end

$version
  2025.1.0
  $dumpfile ("memory_dump.vcd") 
$end

$timescale
  1ps
$end

$scope module tb_bram $end
$var reg 1 ! clka $end
$var reg 1 " ena $end
$var reg 1 # wea $end
$var reg 13 $ addra [12:0] $end
$var reg 8 % dina [7:0] $end
$var wire 8 & douta [7:0] $end
$scope module dut $end
$var wire 1 ' clka $end
$var wire 1 ( ena $end
$var wire 1 ) wea $end
$var wire 11 * addra [10:0] $end
$var wire 8 + dina [7:0] $end
$var reg 8 , douta [7:0] $end
$upscope $end
$scope task write_data $end
$var reg 13 - addr [12:0] $end
$var reg 8 . data [7:0] $end
$upscope $end
$scope task read_data $end
$var reg 13 / addr [12:0] $end
$upscope $end
$upscope $end
$enddefinitions $end

#0
$dumpvars
0!
0"
0#
b0 $
b0 %
bx &
0'
0(
0)
b0 *
b0 +
bx ,
bx -
bx .
bx /
$end

#5000
1!
1'

#10000
0!
0'

#15000
1!
1'

#20000
0!
1"
1#
b10001 %
0'
1(
1)
b10001 +
b0 -
b10001 .

#25000
1!
1'

#30000
0!
0"
0#
0'
0(
0)
b1 -
b100010 .

#35000
1!
1'

#40000
0!
1"
1#
b1 $
b100010 %
0'
1(
1)
b1 *
b100010 +

#45000
1!
1'

#50000
0!
0"
0#
0'
0(
0)
b10 -
b110011 .

#55000
1!
1'

#60000
0!
1"
1#
b10 $
b110011 %
0'
1(
1)
b10 *
b110011 +

#65000
1!
1'

#70000
0!
0"
0#
0'
0(
0)
b11 -
b1000100 .

#75000
1!
1'

#80000
0!
1"
1#
b11 $
b1000100 %
0'
1(
1)
b11 *
b1000100 +

#85000
1!
1'

#90000
0!
0"
0#
0'
0(
0)
b100 -
b1010101 .

#95000
1!
1'

#100000
0!
1"
1#
b100 $
b1010101 %
0'
1(
1)
b100 *
b1010101 +

#105000
1!
1'

#110000
0!
0"
0#
0'
0(
0)
b0 /

#115000
1!
1'

#120000
0!
1"
b0 $
0'
1(
b0 *

#125000
1!
b10001 &
1'
b10001 ,

#130000
0!
0'
b1 /

#135000
1!
1'

#140000
0!
b1 $
0'
b1 *

#145000
1!
b100010 &
1'
b100010 ,

#150000
0!
0'
b10 /

#155000
1!
1'

#160000
0!
b10 $
0'
b10 *

#165000
1!
b110011 &
1'
b110011 ,

#170000
0!
0'
b11 /

#175000
1!
1'

#180000
0!
b11 $
0'
b11 *

#185000
1!
b1000100 &
1'
b1000100 ,

#190000
0!
0'
b100 /

#195000
1!
1'

#200000
0!
b100 $
0'
b100 *

#205000
1!
b1010101 &
1'
b1010101 ,

#210000
0!
b101 $
0'
b101 *
b101 /

#215000
1!
bx &
1'
bx ,

#220000
0!
0'

#225000
1!
1'

#230000
0!
b110 $
0'
b110 *
b110 /

#235000
1!
1'

#240000
0!
0'

#245000
1!
1'

#250000
0!
b111 $
0'
b111 *
b111 /

#255000
1!
1'

#260000
0!
0'

#265000
1!
1'

#270000
0!
b1000 $
0'
b1000 *
b1000 /

#275000
1!
1'

#280000
0!
0'

#285000
1!
1'

#290000
0!
b1001 $
0'
b1001 *
b1001 /

#295000
1!
1'

#300000
0!
0'

#305000
1!
1'

#310000
0!
b1010 $
0'
b1010 *
b1010 /

#315000
1!
1'

#320000
0!
0'

#325000
1!
1'

#330000
0!
b1011 $
0'
b1011 *
b1011 /

#335000
1!
1'

#340000
0!
0'

#345000
1!
1'

#350000
0!
b1100 $
0'
b1100 *
b1100 /

#355000
1!
1'

#360000
0!
0'

#365000
1!
1'

#370000
0!
b1101 $
0'
b1101 *
b1101 /

#375000
1!
1'

#380000
0!
0'

#385000
1!
1'

#390000
0!
b1110 $
0'
b1110 *
b1110 /

#395000
1!
1'

#400000
0!
0'

#405000
1!
1'

#410000
0!
b1111 $
0'
b1111 *
b1111 /

#415000
1!
1'

#420000
0!
0'

#425000
1!
1'

#430000
0!
b10000 $
0'
b10000 *
b10000 /

#435000
1!
1'

#440000
0!
0'

#445000
1!
1'

#450000
0!
b10001 $
0'
b10001 *
b10001 /

#455000
1!
1'

#460000
0!
0'

#465000
1!
1'

#470000
0!
b10010 $
0'
b10010 *
b10010 /

#475000
1!
1'

#480000
0!
0'

#485000
1!
1'

#490000
0!
b10011 $
0'
b10011 *
b10011 /

#495000
1!
1'

#500000
0!
0'

#505000
1!
1'

#510000
0!
b10100 $
0'
b10100 *
b10100 /

