work/test/pipeline_as_shift_reg_test/pipeline_test.v
`timescale 1ns / 1ps
module pipeline_reg (
    input wire clk,
    input wire rst,
    input wire flush,
    input wire stall,

    input wire [7:0] data_i,
    output wire [7:0] data_1,
    output wire [7:0] data_2,
    output wire [7:0] data_3,
    output wire [7:0] data_4
);

    reg [7:0] data_1_reg;
    reg [7:0] data_2_reg;
    reg [7:0] data_3_reg;
    reg [7:0] data_4_reg;
    
    always @(posedge clk or posedge rst) begin
        if (rst) begin
            data_1_reg <= 8'h0;
            data_2_reg <= 8'h0;
            data_3_reg <= 8'h0;
            data_4_reg <= 8'h0;
        end else if (flush) begin
            data_1_reg <= 8'h0;
            data_2_reg <= 8'h0;
            data_3_reg <= 8'h0;
            data_4_reg <= 8'h0;
        end else if (~stall) begin
            data_1_reg <= data_i;
            data_2_reg <= data_1_reg;
            data_3_reg <= data_2_reg;
            data_4_reg <= data_3_reg;
        end
    end

    assign data_1 = data_1_reg;
    assign data_2 = data_2_reg;
    assign data_3 = data_3_reg;
    assign data_4 = data_4_reg;

endmodule

work/test/pipeline_test/tb_pipeline.v
`timescale 1ns / 1ps
module tb_pipeline;

    // DUT signal
    reg clk = 0;
    reg rst = 1;
    reg flush = 0;
    reg stall = 0;
    reg [7:0] data_i = 8'h0;

    wire [7:0] data_1;
    wire [7:0] data_2;
    wire [7:0] data_3;
    wire [7:0] data_4;

    always #5 clk = ~clk;

    pipeline_reg dut (
        .clk(clk),
        .rst(rst),
        .flush(flush),
        .stall(stall),
        .data_i(data_i),
        .data_1(data_1),
        .data_2(data_2),
        .data_3(data_3),
        .data_4(data_4)
    );

    initial begin
        $dumpfile("tb_pipeline.vcd");
        $dumpvars(0, tb_pipeline);
        $display("===test pipeline===");
        $display("=== testbench   ===");
    end

    initial begin 
        $display("[%0t] rst = %0b flush = %0b stall = %0b data_i = %08x data_1 = %08x data_2 = %08x data_3 = %08x data_4 = %08x", $time, rst, flush, stall, data_i, data_1, data_2, data_3, data_4);
        #20; rst = 0; data_i = 8'h44;
        $display("[%0t] rst = %0b flush = %0b stall = %0b data_i = %08x data_1 = %08x data_2 = %08x data_3 = %08x data_4 = %08x", $time, rst, flush, stall, data_i, data_1, data_2, data_3, data_4);
        #10; data_i = 8'h33;
        $display("[%0t] rst = %0b flush = %0b stall = %0b data_i = %08x data_1 = %08x data_2 = %08x data_3 = %08x data_4 = %08x", $time, rst, flush, stall, data_i, data_1, data_2, data_3, data_4);
        #10; data_i = 8'h22;
        $display("[%0t] rst = %0b flush = %0b stall = %0b data_i = %08x data_1 = %08x data_2 = %08x data_3 = %08x data_4 = %08x", $time, rst, flush, stall, data_i, data_1, data_2, data_3, data_4);
        #10; data_i = 8'h11;
        $display("[%0t] rst = %0b flush = %0b stall = %0b data_i = %08x data_1 = %08x data_2 = %08x data_3 = %08x data_4 = %08x", $time, rst, flush, stall, data_i, data_1, data_2, data_3, data_4);
        #10; data_i = 8'hFF; flush = 1;
        $display("[%0t] rst = %0b flush = %0b stall = %0b data_i = %08x data_1 = %08x data_2 = %08x data_3 = %08x data_4 = %08x", $time, rst, flush, stall, data_i, data_1, data_2, data_3, data_4);
        #20; data_i = 8'hAA; flush = 0;
        $display("[%0t] rst = %0b flush = %0b stall = %0b data_i = %08x data_1 = %08x data_2 = %08x data_3 = %08x data_4 = %08x", $time, rst, flush, stall, data_i, data_1, data_2, data_3, data_4);
        #30; data_i = 8'hBB; stall = 1;
        $display("[%0t] rst = %0b flush = %0b stall = %0b data_i = %08x data_1 = %08x data_2 = %08x data_3 = %08x data_4 = %08x", $time, rst, flush, stall, data_i, data_1, data_2, data_3, data_4);
        #20; data_i = 8'hCC; stall = 0;
        $display("[%0t] rst = %0b flush = %0b stall = %0b data_i = %08x data_1 = %08x data_2 = %08x data_3 = %08x data_4 = %08x", $time, rst, flush, stall, data_i, data_1, data_2, data_3, data_4);
        #10; data_i = 8'hDD;
        $display("[%0t] rst = %0b flush = %0b stall = %0b data_i = %08x data_1 = %08x data_2 = %08x data_3 = %08x data_4 = %08x", $time, rst, flush, stall, data_i, data_1, data_2, data_3, data_4);
        #40;
        $display("[%0t] rst = %0b flush = %0b stall = %0b data_i = %08x data_1 = %08x data_2 = %08x data_3 = %08x data_4 = %08x", $time, rst, flush, stall, data_i, data_1, data_2, data_3, data_4);
        $display("=== test finish ===");
        $finish;
    end

endmodule

work/test/pipeline_test/tb_pipeline.vcd
$date
	Sat Oct 18 02:05:03 2025
$end
$version
	Icarus Verilog
$end
$timescale
	1ps
$end
$scope module tb_pipeline $end
$var wire 8 ! data_4 [7:0] $end
$var wire 8 " data_3 [7:0] $end
$var wire 8 # data_2 [7:0] $end
$var wire 8 $ data_1 [7:0] $end
$var reg 1 % clk $end
$var reg 8 & data_i [7:0] $end
$var reg 1 ' flush $end
$var reg 1 ( rst $end
$var reg 1 ) stall $end
$scope module dut $end
$var wire 1 % clk $end
$var wire 8 * data_1 [7:0] $end
$var wire 8 + data_2 [7:0] $end
$var wire 8 , data_3 [7:0] $end
$var wire 8 - data_4 [7:0] $end
$var wire 8 . data_i [7:0] $end
$var wire 1 ' flush $end
$var wire 1 ( rst $end
$var wire 1 ) stall $end
$var reg 8 / data_1_reg [7:0] $end
$var reg 8 0 data_2_reg [7:0] $end
$var reg 8 1 data_3_reg [7:0] $end
$var reg 8 2 data_4_reg [7:0] $end
$upscope $end
$upscope $end
$enddefinitions $end
$comment Show the parameter values. $end
$dumpall
$end
#0
$dumpvars
b0 2
b0 1
b0 0
b0 /
b0 .
b0 -
b0 ,
b0 +
b0 *
0)
1(
0'
b0 &
0%
b0 $
b0 #
b0 "
b0 !
$end
#5000
1%
#10000
0%
#15000
1%
#20000
0%
b1000100 &
b1000100 .
0(
#25000
b1000100 $
b1000100 *
b1000100 /
1%
#30000
0%
b110011 &
b110011 .
#35000
b1000100 #
b1000100 +
b1000100 0
b110011 $
b110011 *
b110011 /
1%
#40000
0%
b100010 &
b100010 .
#45000
b1000100 "
b1000100 ,
b1000100 1
b110011 #
b110011 +
b110011 0
b100010 $
b100010 *
b100010 /
1%
#50000
0%
b10001 &
b10001 .
#55000
b1000100 !
b1000100 -
b1000100 2
b110011 "
b110011 ,
b110011 1
b100010 #
b100010 +
b100010 0
b10001 $
b10001 *
b10001 /
1%
#60000
0%
1'
b11111111 &
b11111111 .
#65000
b0 !
b0 -
b0 2
b0 "
b0 ,
b0 1
b0 #
b0 +
b0 0
b0 $
b0 *
b0 /
1%
#70000
0%
#75000
1%
#80000
0%
0'
b10101010 &
b10101010 .
#85000
b10101010 $
b10101010 *
b10101010 /
1%
#90000
0%
#95000
b10101010 #
b10101010 +
b10101010 0
1%
#100000
0%
#105000
b10101010 "
b10101010 ,
b10101010 1
1%
#110000
0%
1)
b10111011 &
b10111011 .
#115000
1%
#120000
0%
#125000
1%
#130000
0%
0)
b11001100 &
b11001100 .
#135000
b10101010 !
b10101010 -
b10101010 2
b11001100 $
b11001100 *
b11001100 /
1%
#140000
0%
b11011101 &
b11011101 .
#145000
b11001100 #
b11001100 +
b11001100 0
b11011101 $
b11011101 *
b11011101 /
1%
#150000
0%
#155000
b11001100 "
b11001100 ,
b11001100 1
b11011101 #
b11011101 +
b11011101 0
1%
#160000
0%
#165000
b11001100 !
b11001100 -
b11001100 2
b11011101 "
b11011101 ,
b11011101 1
1%
#170000
0%
#175000
b11011101 !
b11011101 -
b11011101 2
1%
